{"stat.chestOpened":3,"stat.pickup.minecraft.bone":2,"stat.leaveGame":6,"stat.pickup.minecraft.gravel":47,"stat.pickup.minecraft.arrow":2,"stat.useItem.minecraft.chicken":5,"stat.pickup.minecraft.flint":9,"stat.useItem.minecraft.apple":2,"stat.mineBlock.minecraft.brown_mushroom":2,"stat.useItem.minecraft.porkchop":2,"stat.useItem.minecraft.rotten_flesh":7,"stat.breakItem.minecraft.wooden_sword":1,"stat.jump":717,"stat.swimOneCm":1706,"stat.fallOneCm":6073,"stat.useItem.minecraft.planks":1,"stat.climbOneCm":968,"stat.pickup.minecraft.carrot":3,"stat.pickup.minecraft.porkchop":2,"stat.useItem.minecraft.dirt":54,"stat.pickup.minecraft.dirt":64,"stat.pickup.minecraft.bow":1,"achievement.exploreAllBiomes":{"value":0,"progress":["Beach","Birch Forest","Roofed Forest","Plains","Swampland"]},"stat.craftingTableInteraction":15,"stat.pickup.minecraft.rotten_flesh":9,"stat.craftItem.minecraft.furnace":1,"stat.useItem.minecraft.egg":2,"stat.mineBlock.minecraft.leaves2":8,"stat.mineBlock.minecraft.log2":8,"stat.pickup.minecraft.wooden_pickaxe":2,"stat.damageTaken":1071,"stat.pickup.minecraft.feather":4,"stat.pickup.minecraft.leather":8,"stat.craftItem.minecraft.stone_pickaxe":2,"stat.mineBlock.minecraft.torch":1,"stat.mineBlock.minecraft.red_flower":1,"stat.useItem.minecraft.wooden_pickaxe":41,"stat.useItem.minecraft.furnace":1,"stat.pickup.minecraft.cobblestone":22,"stat.craftItem.minecraft.wooden_sword":3,"stat.pickup.minecraft.log2":8,"stat.pickup.minecraft.wooden_hoe":1,"stat.pickup.minecraft.planks":6,"stat.entityKilledBy.ZombieVillager":1,"stat.craftItem.minecraft.stone_sword":1,"stat.flyOneCm":3592,"stat.pickup.minecraft.wheat_seeds":14,"stat.pickup.minecraft.brown_mushroom":3,"stat.pickup.minecraft.potato":3,"stat.mineBlock.minecraft.gravel":38,"stat.craftItem.minecraft.wooden_hoe":1,"stat.useItem.minecraft.stone_sword":21,"stat.damageDealt":1715,"stat.timeSinceDeath":176116,"stat.killEntity.Cow":4,"stat.mineBlock.minecraft.dirt":59,"stat.useItem.minecraft.crafting_table":2,"stat.craftItem.minecraft.wooden_pickaxe":3,"stat.killEntity.Pig":1,"stat.walkOneCm":473245,"stat.pickup.minecraft.stick":12,"stat.pickup.minecraft.crafting_table":1,"stat.pickup.minecraft.wooden_shovel":1,"stat.craftItem.minecraft.crafting_table":1,"stat.furnaceInteraction":16,"stat.useItem.minecraft.gravel":19,"stat.killEntity.ZombieVillager":1,"stat.pickup.minecraft.wooden_sword":2,"stat.pickup.minecraft.log":7,"stat.pickup.minecraft.beef":7,"stat.pickup.minecraft.chicken":5,"achievement.mineWood":7,"stat.pickup.minecraft.sapling":1,"stat.sprintOneCm":1320,"stat.craftItem.minecraft.stick":16,"stat.killEntity.Skeleton":1,"achievement.openInventory":29,"stat.craftItem.minecraft.planks":30,"stat.killEntity.Chicken":5,"stat.useItem.minecraft.wheat_seeds":10,"stat.mineBlock.minecraft.crafting_table":1,"stat.mobKills":16,"stat.mineBlock.minecraft.log":9,"stat.useItem.minecraft.beef":7,"stat.mineBlock.minecraft.planks":1,"stat.deaths":1,"stat.pickup.minecraft.egg":5,"stat.mineBlock.minecraft.leaves":9,"stat.playOneMinute":217069,"stat.useItem.minecraft.wooden_sword":109,"stat.craftItem.minecraft.wooden_shovel":1,"stat.pickup.minecraft.torch":1,"stat.pickup.minecraft.red_flower":1,"stat.killEntity.Zombie":3,"stat.mineBlock.minecraft.stone":17,"stat.mineBlock.minecraft.tallgrass":12,"stat.pickup.minecraft.wheat":14}